{
  "game": {
    "name": "Эволюционная Адаптация: Генетический Резонанс",
    "version": "1.0.0",
    "description": "Игра про эволюционную адаптацию сущностей с обучением и генетическими модификациями"
  },
  "display": {
    "width": 1280,
    "height": 720,
    "fullscreen": false,
    "vsync": true,
    "fps_limit": 60,
    "ui_scale": 1.0
  },
  "audio": {
    "master_volume": 0.8,
    "music_volume": 0.6,
    "sfx_volume": 0.7,
    "voice_volume": 0.8,
    "enable_audio": true
  },
  "graphics": {
    "quality": "high",
    "shadows": true,
    "particles": true,
    "bloom": true,
    "antialiasing": true,
    "texture_filtering": "anisotropic"
  },
  "gameplay": {
    "difficulty": "normal",
    "auto_save": true,
    "save_interval": 300,
    "max_saves": 10,
    "tutorial_enabled": true,
    "ai_learning_rate": 0.1,
    "evolution_speed": 1.0
  },
  "combat": {
    "damage_multiplier": 1.0,
    "defense_multiplier": 1.0,
    "critical_chance_base": 0.05,
    "critical_multiplier_base": 1.5,
    "dodge_chance_base": 0.1,
    "block_chance_base": 0.15,
    "parry_chance_base": 0.08
  },
  "evolution": {
    "mutation_rate": 0.1,
    "mutation_intensity": 0.5,
    "genetic_stability": 0.8,
    "adaptation_speed": 1.0,
    "max_generations": 100,
    "inheritance_rate": 0.7
  },
  "ai": {
    "learning_enabled": true,
    "memory_capacity": 1000,
    "decision_threshold": 0.6,
    "exploration_rate": 0.2,
    "adaptation_speed": 0.1,
    "personality_stability": 0.8
  },
  "world": {
    "generation_seed": 0,
    "biome_variety": 0.8,
    "enemy_density": 1.0,
    "item_density": 0.7,
    "weather_intensity": 0.6,
    "time_scale": 1.0
  },
  "economy": {
    "gold_multiplier": 1.0,
    "experience_multiplier": 1.0,
    "loot_quality": 1.0,
    "merchant_prices": 1.0,
    "repair_costs": 1.0
  },
  "interface": {
    "language": "ru",
    "font_size": "medium",
    "tooltip_delay": 0.5,
    "show_damage_numbers": true,
    "show_health_bars": true,
    "show_minimap": true,
    "show_quest_log": true
  },
  "controls": {
    "keyboard": {
      "move_up": "W",
      "move_down": "S",
      "move_left": "A",
      "move_right": "D",
      "attack": "SPACE",
      "interact": "E",
      "inventory": "I",
      "character": "C",
      "map": "M",
      "pause": "ESC"
    },
    "gamepad": {
      "deadzone": 0.1,
      "vibration": true,
      "sensitivity": 1.0
    }
  },
  "debug": {
    "enabled": false,
    "show_fps": false,
    "show_hitboxes": false,
    "show_pathfinding": false,
    "god_mode": false,
    "infinite_resources": false
  },
  "performance": {
    "max_entities": 1000,
    "max_particles": 500,
    "max_effects": 200,
    "lod_distance": 1000,
    "culling_enabled": true,
    "multithreading": true
  }
}
